{"cameraMode":{"drawMode":0,"name":"Shaded","section":"Shading Mode"},"sceneLighting":true,"audioPlay":false,"sceneViewState":{"showFog":true,"showMaterialUpdate":true,"showSkybox":true,"showFlares":true,"showImageEffects":true,"showParticleSystems":true,"showVisualEffectGraphs":true,"m_FxEnabled":true},"in2DMode":false,"pivot":{"x":-58.8298454284668,"y":4.894000053405762,"z":4.09499979019165},"rotation":{"x":0.026305923238396646,"y":0.6032639741897583,"z":-0.019914817065000535,"w":0.7968578338623047},"size":13.616643905639649,"orthographic":false}