{"cameraMode":{"drawMode":0,"name":"Shaded","section":"Shading Mode"},"sceneLighting":true,"audioPlay":false,"sceneViewState":{"showFog":true,"showMaterialUpdate":true,"showSkybox":true,"showFlares":true,"showImageEffects":true,"showParticleSystems":true,"showVisualEffectGraphs":true,"m_FxEnabled":false},"in2DMode":false,"pivot":{"x":-62.203922271728519,"y":-0.26081085205078127,"z":3.729633331298828},"rotation":{"x":-0.15489982068538667,"y":0.7487463355064392,"z":-0.6164918541908264,"w":-0.18831199407577516},"size":3.331545352935791,"orthographic":false}