{"cameraMode":{"drawMode":0,"name":"Shaded","section":"Shading Mode"},"sceneLighting":true,"audioPlay":false,"sceneViewState":{"showFog":true,"showMaterialUpdate":true,"showSkybox":true,"showFlares":true,"showImageEffects":true,"showParticleSystems":true,"showVisualEffectGraphs":true,"m_FxEnabled":true},"in2DMode":false,"pivot":{"x":39.38275146484375,"y":5.625951766967773,"z":-10.306785583496094},"rotation":{"x":0.02703016623854637,"y":0.9484004378318787,"z":-0.10524634271860123,"w":0.3010987639427185},"size":10.876068115234375,"orthographic":false}